lockss/pybasic/__init__.py
lockss/pybasic/cliutil.py
lockss/pybasic/errorutil.py
lockss/pybasic/fileutil.py
lockss/pybasic/outpututil.py
lockss_pybasic-0.1.1.dist-info/LICENSE
lockss_pybasic-0.1.1.dist-info/METADATA
lockss_pybasic-0.1.1.dist-info/WHEEL
lockss_pybasic-0.1.1.dist-info/RECORD
