Metadata-Version: 2.3
Name: lockss-pybasic
Version: 0.1.1
Summary: Basic Python utilities
License: BSD-3-Clause
Author: Thib Guicherd-Callin
Author-email: thib@cs.stanford.edu
Maintainer: Thib Guicherd-Callin
Maintainer-email: thib@cs.stanford.edu
Requires-Python: >=3.9,<4.0
Classifier: Development Status :: 4 - Beta
Classifier: Environment :: Console
Classifier: Framework :: Pydantic :: 2
Classifier: Intended Audience :: Developers
Classifier: License :: OSI Approved :: BSD License
Classifier: Programming Language :: Python
Classifier: Topic :: Software Development :: Libraries
Requires-Dist: pydantic (>=2.11.0,<3.0.0)
Requires-Dist: pydantic-argparse (>=0.10.0,<0.11.0)
Requires-Dist: rich-argparse (>=1.7.0,<1.8.0)
Requires-Dist: tabulate (>=0.9.0,<0.10.0)
Project-URL: Repository, https://github.com/lockss/lockss-pybasic
